winzy_horoscope/__init__.py
winzy_horoscope-0.0.1.dist-info/LICENSE
winzy_horoscope-0.0.1.dist-info/METADATA
winzy_horoscope-0.0.1.dist-info/WHEEL
winzy_horoscope-0.0.1.dist-info/entry_points.txt
winzy_horoscope-0.0.1.dist-info/top_level.txt
winzy_horoscope-0.0.1.dist-info/RECORD
