Metadata-Version: 2.1
Name: winzy-horoscope
Version: 0.0.1
Summary: Get daily Horoscope using https://horoscope-app-api.vercel.app by Ashutosh Krishna
Author: Sukhbinder Singh
License: Apache-2.0
Project-URL: Homepage, https://github.com/sukhbinder/winzy-horoscope
Project-URL: Changelog, https://github.com/sukhbinder/winzy-horoscope/releases
Project-URL: Issues, https://github.com/sukhbinder/winzy-horoscope/issues
Project-URL: CI, https://github.com/sukhbinder/winzy-horoscope/actions
Classifier: License :: OSI Approved :: Apache Software License
License-File: LICENSE
Requires-Dist: winzy
Requires-Dist: colorama
Requires-Dist: requests
Provides-Extra: test
Requires-Dist: pytest; extra == "test"
